cafeden/__init__.py
cafeden/__main__.py
cafeden/cafeden.py
cafeden/config.py
cafeden/resources/icon.ico
resources/icon.ico
cafeden-0.2.0.dist-info/LICENSE
cafeden-0.2.0.dist-info/METADATA
cafeden-0.2.0.dist-info/WHEEL
cafeden-0.2.0.dist-info/entry_points.txt
cafeden-0.2.0.dist-info/top_level.txt
cafeden-0.2.0.dist-info/RECORD
