Metadata-Version: 2.1
Name: cafeden
Version: 0.2.0
Summary: Simple auto-clicker for keeping your computer awake
Home-page: https://github.com/coredumplabs/cafeden
Author: Coredump Labs
Author-email: info@coredumplabs.com
License: MIT License
Download-URL: https://github.com/coredumplabs/cafeden/releases/tag/v0.2.0
Platform: UNKNOWN
Classifier: License :: OSI Approved :: MIT License
Classifier: Programming Language :: Python :: 3.7
Classifier: Programming Language :: Python :: 3.8
Classifier: Programming Language :: Python :: 3.9
Classifier: Programming Language :: Python :: Implementation :: CPython
Requires-Dist: keyboard
Requires-Dist: mouse
Requires-Dist: pystray
Requires-Dist: pillow
